LICENSE.txt
README.md
setup.cfg
setup.py
kidbit_assistant/__init__.py
kidbit_assistant/audio.py
kidbit_assistant/example_audio.py
kidbit_assistant/example_vision.py
kidbit_assistant/main.py
kidbit_assistant/vision.py
kidbit_assistant.egg-info/PKG-INFO
kidbit_assistant.egg-info/SOURCES.txt
kidbit_assistant.egg-info/dependency_links.txt
kidbit_assistant.egg-info/requires.txt
kidbit_assistant.egg-info/top_level.txt