Metadata-Version: 2.1
Name: kidbit-assistant
Version: 1.2.2
Summary: Design your Own Assistant
Home-page: https://github.com/KidBit-Academy/kidbit_assistant
Author: KidBit
Author-email: kidbitacademy@gmail.com
License: MIT
Download-URL: https://github.com/KidBit-Academy/kidbit_assistant/archive/refs/tags/v1.2.2.tar.gz
Keywords: ALEXA,BOT,CODING,KIDS,KIDBIT,ASSISTANT
Platform: UNKNOWN
Classifier: Development Status :: 3 - Alpha
Classifier: Intended Audience :: Developers
Classifier: Topic :: Software Development :: Build Tools
Classifier: License :: OSI Approved :: MIT License
Classifier: Programming Language :: Python :: 3
Classifier: Programming Language :: Python :: 3.4
Classifier: Programming Language :: Python :: 3.5
Classifier: Programming Language :: Python :: 3.6
Requires-Python: >=3.6
License-File: LICENSE.txt
